{
    "302": {
        "depressed": "no",
        "phq_score": "4",
        "gender": "male",
        "f0_median": 144.7269237440378,
        "f0_mean": 144.6545967069565,
        "f0_range": 78.91147698331937,
        "zcr_median": 0.048828125,
        "zcr_mean": 0.05812886880990415,
        "rmse_median": 0.005208232440054417,
        "rmse_mean": 0.005469248164445162,
        "ber_median": 76.609375,
        "ber_mean": 130.91868591308594
    },
    "307": {
        "depressed": "no",
        "phq_score": "4",
        "gender": "female",
        "f0_median": 287.786716002164,
        "f0_mean": 292.0970199330258,
        "f0_range": 176.23130825861463,
        "zcr_median": 0.0625,
        "zcr_mean": 0.07136394269169329,
        "rmse_median": 0.05402730405330658,
        "rmse_mean": 0.05996621400117874,
        "ber_median": 63.30357360839844,
        "ber_mean": 223.79420471191406
    },
    "331": {
        "depressed": "no",
        "phq_score": "8",
        "gender": "male",
        "f0_median": 150.26468791756287,
        "f0_mean": 155.29623043448285,
        "f0_range": 199.2020306822728,
        "zcr_median": 0.05078125,
        "zcr_mean": 0.059482952276357824,
        "rmse_median": 0.004692423157393932,
        "rmse_mean": 0.006321998313069344,
        "ber_median": 20.809579849243164,
        "ber_mean": 111.4858627319336
    },
    "335": {
        "depressed": "yes",
        "phq_score": "12",
        "gender": "female",
        "f0_median": 253.44393965741244,
        "f0_mean": 252.53075370166536,
        "f0_range": 264.18275561726784,
        "zcr_median": 0.0517578125,
        "zcr_mean": 0.09739416932907348,
        "rmse_median": 0.003138456027954817,
        "rmse_mean": 0.0038943046238273382,
        "ber_median": 38.15788269042969,
        "ber_mean": 172.16343688964844
    },
    "346": {
        "depressed": "yes",
        "phq_score": "23",
        "gender": "female",
        "f0_median": 250.53288772482563,
        "f0_mean": 229.03570554510114,
        "f0_range": 236.73107975123213,
        "zcr_median": 0.048828125,
        "zcr_mean": 0.07977548422523961,
        "rmse_median": 0.002242988906800747,
        "rmse_mean": 0.0031205867417156696,
        "ber_median": 50.005035400390625,
        "ber_mean": 218.398681640625
    },
    "367": {
        "depressed": "yes",
        "phq_score": "19",
        "gender": "male",
        "f0_median": 186.60659830736148,
        "f0_mean": 190.67239194130454,
        "f0_range": 355.21790944335936,
        "zcr_median": 0.04296875,
        "zcr_mean": 0.052759335063897767,
        "rmse_median": 0.005233380012214184,
        "rmse_mean": 0.0067648072727024555,
        "ber_median": 98.60830688476562,
        "ber_mean": 672.0714721679688
    },
    "377": {
        "depressed": "yes",
        "phq_score": "16",
        "gender": "female",
        "f0_median": 227.10088581417543,
        "f0_mean": 239.00314797334445,
        "f0_range": 397.5945473075515,
        "zcr_median": 0.0390625,
        "zcr_mean": 0.10727211461661341,
        "rmse_median": 0.002041273983195424,
        "rmse_mean": 0.0023286400828510523,
        "ber_median": 110.42790222167969,
        "ber_mean": 533.7650756835938
    },
    "381": {
        "depressed": "yes",
        "phq_score": "16",
        "gender": "male",
        "f0_median": 139.39440770106785,
        "f0_mean": 189.49924623261018,
        "f0_range": 340.62881471566794,
        "zcr_median": 0.052734375,
        "zcr_mean": 0.08414037539936102,
        "rmse_median": 0.002627940848469734,
        "rmse_mean": 0.004362910520285368,
        "ber_median": 31.60734748840332,
        "ber_mean": 2742.096923828125
    },
    "382": {
        "depressed": "no",
        "phq_score": "0",
        "gender": "male",
        "f0_median": 132.33298265557312,
        "f0_mean": 142.94219456585947,
        "f0_range": 312.6044455729052,
        "zcr_median": 0.046875,
        "zcr_mean": 0.06288064097444089,
        "rmse_median": 0.0077649252489209175,
        "rmse_mean": 0.009600481018424034,
        "ber_median": 55.156578063964844,
        "ber_mean": 266.3560791015625
    },
    "388": {
        "depressed": "yes",
        "phq_score": "17",
        "gender": "male",
        "f0_median": 126.72196982870621,
        "f0_mean": 131.88991699440967,
        "f0_range": 324.66583832778434,
        "zcr_median": 0.044921875,
        "zcr_mean": 0.07556035343450479,
        "rmse_median": 0.003808820154517889,
        "rmse_mean": 0.005787339992821217,
        "ber_median": 50.55900573730469,
        "ber_mean": 1236.010986328125
    },
    "389": {
        "depressed": "yes",
        "phq_score": "14",
        "gender": "male",
        "f0_median": 152.4497023255762,
        "f0_mean": 148.4217415364332,
        "f0_range": 79.23847258976912,
        "zcr_median": 0.015625,
        "zcr_mean": 0.028629193290734826,
        "rmse_median": 0.004679642617702484,
        "rmse_mean": 0.006458303891122341,
        "ber_median": 438.92523193359375,
        "ber_mean": 1714.6346435546875
    },
    "390": {
        "depressed": "no",
        "phq_score": "9",
        "gender": "male",
        "f0_median": 131.9507910772894,
        "f0_mean": 141.76340368409404,
        "f0_range": 354.74992971675135,
        "zcr_median": 0.029296875,
        "zcr_mean": 0.04675643969648562,
        "rmse_median": 0.0024793094489723444,
        "rmse_mean": 0.0034271166659891605,
        "ber_median": 128.25137329101562,
        "ber_mean": 614.6997680664062
    },
    "395": {
        "depressed": "no",
        "phq_score": "7",
        "gender": "female",
        "f0_median": 219.36499593892518,
        "f0_mean": 225.2878199255076,
        "f0_range": 274.2767026072177,
        "zcr_median": 0.044921875,
        "zcr_mean": 0.06759185303514377,
        "rmse_median": 0.003639522008597851,
        "rmse_mean": 0.004096447490155697,
        "ber_median": 56.74987030029297,
        "ber_mean": 325.90557861328125
    },
    "403": {
        "depressed": "no",
        "phq_score": "0",
        "gender": "female",
        "f0_median": 249.08992447176465,
        "f0_mean": 253.98601634707157,
        "f0_range": 215.50505108459276,
        "zcr_median": 0.0625,
        "zcr_mean": 0.08231829073482429,
        "rmse_median": 0.01209496520459652,
        "rmse_mean": 0.016995910555124283,
        "ber_median": 28.204395294189453,
        "ber_mean": 369.08697509765625
    },
    "404": {
        "depressed": "no",
        "phq_score": "0",
        "gender": "male",
        "f0_median": 132.71517423385683,
        "f0_mean": 143.69506094944185,
        "f0_range": 365.76185708500213,
        "zcr_median": 0.041015625,
        "zcr_mean": 0.056727985223642176,
        "rmse_median": 0.001851097447797656,
        "rmse_mean": 0.004133174195885658,
        "ber_median": 69.80396270751953,
        "ber_mean": 269.89251708984375
    },
    "406": {
        "depressed": "no",
        "phq_score": "2",
        "gender": "female",
        "f0_median": 282.842712474619,
        "f0_mean": 288.52026168971514,
        "f0_range": 371.93156996853287,
        "zcr_median": 0.046875,
        "zcr_mean": 0.06330184205271565,
        "rmse_median": 0.007410885766148567,
        "rmse_mean": 0.008352409116923809,
        "ber_median": 50.39982604980469,
        "ber_mean": 505.98431396484375
    },
    "413": {
        "depressed": "yes",
        "phq_score": "10",
        "gender": "female",
        "f0_median": 214.35469250725862,
        "f0_mean": 213.0668662820338,
        "f0_range": 361.76334515538946,
        "zcr_median": 0.052734375,
        "zcr_mean": 0.06711761182108626,
        "rmse_median": 0.005854884162545204,
        "rmse_mean": 0.006582758855074644,
        "ber_median": 36.60658264160156,
        "ber_mean": 353.9973449707031
    },
    "417": {
        "depressed": "no",
        "phq_score": "7",
        "gender": "female",
        "f0_median": 221.91389441356898,
        "f0_mean": 233.88989465837716,
        "f0_range": 197.54257971304025,
        "zcr_median": 0.052734375,
        "zcr_mean": 0.10085113817891374,
        "rmse_median": 0.002740344498306513,
        "rmse_mean": 0.003371694590896368,
        "ber_median": 48.2716064453125,
        "ber_mean": 241.57118225097656
    },
    "418": {
        "depressed": "yes",
        "phq_score": "10",
        "gender": "female",
        "f0_median": 243.40070273411817,
        "f0_mean": 249.37399610856767,
        "f0_range": 264.19706515231303,
        "zcr_median": 0.04296875,
        "zcr_mean": 0.054163338658146966,
        "rmse_median": 0.005690061487257481,
        "rmse_mean": 0.0077895005233585835,
        "ber_median": 107.40644836425781,
        "ber_mean": 423.638671875
    },
    "420": {
        "depressed": "no",
        "phq_score": "3",
        "gender": "male",
        "f0_median": 142.24060181972814,
        "f0_mean": 143.78461283740432,
        "f0_range": 321.66191669175817,
        "zcr_median": 0.037109375,
        "zcr_mean": 0.06508648662140575,
        "rmse_median": 0.004579066298902035,
        "rmse_mean": 0.005803980398923159,
        "ber_median": 103.03916931152344,
        "ber_mean": 505.98272705078125
    },
    "422": {
        "depressed": "yes",
        "phq_score": "12",
        "gender": "female",
        "f0_median": 259.3679109302019,
        "f0_mean": 242.27232334171873,
        "f0_range": 318.4274882696387,
        "zcr_median": 0.048828125,
        "zcr_mean": 0.06882425619009584,
        "rmse_median": 0.0027532456442713737,
        "rmse_mean": 0.003365002106875181,
        "ber_median": 54.11425018310547,
        "ber_mean": 270.5014953613281
    },
    "436": {
        "depressed": "no",
        "phq_score": "0",
        "gender": "male",
        "f0_median": 146.40856959456255,
        "f0_mean": 148.7126266163781,
        "f0_range": 74.58836273608759,
        "zcr_median": 0.044921875,
        "zcr_mean": 0.05031012879392971,
        "rmse_median": 0.001423478126525879,
        "rmse_mean": 0.0015542448963969946,
        "ber_median": 43.515586853027344,
        "ber_mean": 171.65667724609375
    },
    "439": {
        "depressed": "no",
        "phq_score": "1",
        "gender": "female",
        "f0_median": 260.1191624416574,
        "f0_mean": 268.3563892611252,
        "f0_range": 376.2414828728998,
        "zcr_median": 0.056640625,
        "zcr_mean": 0.06946697783546325,
        "rmse_median": 0.005443721078336239,
        "rmse_mean": 0.007562961895018816,
        "ber_median": 36.35538864135742,
        "ber_mean": 281.20147705078125
    },
    "440": {
        "depressed": "yes",
        "phq_score": "19",
        "gender": "female",
        "f0_median": 262.38162088748976,
        "f0_mean": 260.24508785479003,
        "f0_range": 168.1792830507429,
        "zcr_median": 0.044921875,
        "zcr_mean": 0.08071460662939298,
        "rmse_median": 0.001956108259037137,
        "rmse_mean": 0.0022835894487798214,
        "ber_median": 53.31455612182617,
        "ber_mean": 285.32806396484375
    },
    "451": {
        "depressed": "no",
        "phq_score": "4",
        "gender": "female",
        "f0_median": 202.3238880603845,
        "f0_mean": 206.50128804749804,
        "f0_range": 219.19815053911478,
        "zcr_median": 0.048828125,
        "zcr_mean": 0.08455533646166134,
        "rmse_median": 0.003357526147738099,
        "rmse_mean": 0.0042951880022883415,
        "ber_median": 63.94359588623047,
        "ber_mean": 278.5024108886719
    },
    "458": {
        "depressed": "no",
        "phq_score": "5",
        "gender": "female",
        "f0_median": 270.06998923363795,
        "f0_mean": 282.5744191218067,
        "f0_range": 277.2089976179246,
        "zcr_median": 0.064453125,
        "zcr_mean": 0.11340605031948882,
        "rmse_median": 0.009165775030851364,
        "rmse_mean": 0.008748753927648067,
        "ber_median": 32.5262336730957,
        "ber_mean": 240.91558837890625
    },
    "472": {
        "depressed": "no",
        "phq_score": "3",
        "gender": "female",
        "f0_median": 317.4802103936399,
        "f0_mean": 313.15229571769396,
        "f0_range": 277.34258090411095,
        "zcr_median": 0.05078125,
        "zcr_mean": 0.08006876497603833,
        "rmse_median": 0.0050923023372888565,
        "rmse_mean": 0.006181263364851475,
        "ber_median": 61.82667541503906,
        "ber_mean": 582.26904296875
    },
    "476": {
        "depressed": "no",
        "phq_score": "3",
        "gender": "male",
        "f0_median": 153.33283446696007,
        "f0_mean": 154.68574980386546,
        "f0_range": 162.039196207443,
        "zcr_median": 0.0458984375,
        "zcr_mean": 0.09399024061501597,
        "rmse_median": 0.002093197777867317,
        "rmse_mean": 0.0027612934354692698,
        "ber_median": 87.436767578125,
        "ber_mean": 324.7386169433594
    },
    "477": {
        "depressed": "no",
        "phq_score": "2",
        "gender": "female",
        "f0_median": 264.66596531114624,
        "f0_mean": 278.7020921271526,
        "f0_range": 263.2929939853998,
        "zcr_median": 0.06640625,
        "zcr_mean": 0.12984225239616615,
        "rmse_median": 0.003470535622909665,
        "rmse_mean": 0.0061716646887362,
        "ber_median": 16.810535430908203,
        "ber_mean": 203.5358428955078
    },
    "482": {
        "depressed": "no",
        "phq_score": "1",
        "gender": "male",
        "f0_median": 146.83263770230758,
        "f0_mean": 155.20623589407901,
        "f0_range": 155.22155333498262,
        "zcr_median": 0.0390625,
        "zcr_mean": 0.057039986022364216,
        "rmse_median": 0.004211816005408764,
        "rmse_mean": 0.00472291000187397,
        "ber_median": 99.74418640136719,
        "ber_mean": 433.6933898925781
    },
    "483": {
        "depressed": "yes",
        "phq_score": "15",
        "gender": "male",
        "f0_median": 221.91389441356898,
        "f0_mean": 235.7140087616213,
        "f0_range": 308.8082442819492,
        "zcr_median": 0.056640625,
        "zcr_mean": 0.08776582468051118,
        "rmse_median": 0.005456267856061459,
        "rmse_mean": 0.006368496920913458,
        "ber_median": 35.35965347290039,
        "ber_mean": 1021.3258666992188
    },
    "484": {
        "depressed": "no",
        "phq_score": "9",
        "gender": "female",
        "f0_median": 239.21922434748075,
        "f0_mean": 246.2417191893253,
        "f0_range": 204.03003385829496,
        "zcr_median": 0.05859375,
        "zcr_mean": 0.08210925019968052,
        "rmse_median": 0.0023158537223935127,
        "rmse_mean": 0.0024437240790575743,
        "ber_median": 26.16326141357422,
        "ber_mean": 164.54342651367188
    },
    "489": {
        "depressed": "no",
        "phq_score": "3",
        "gender": "male",
        "f0_median": 137.3953647458089,
        "f0_mean": 159.3148258640688,
        "f0_range": 365.3649637847138,
        "zcr_median": 0.05859375,
        "zcr_mean": 0.08603734025559105,
        "rmse_median": 0.007936526089906693,
        "rmse_mean": 0.010776109993457794,
        "ber_median": 25.890064239501953,
        "ber_mean": 194.69017028808594
    },
    "490": {
        "depressed": "no",
        "phq_score": "2",
        "gender": "male",
        "f0_median": 130.0595812208287,
        "f0_mean": 133.29452165574892,
        "f0_range": 129.90859534426238,
        "zcr_median": 0.05859375,
        "zcr_mean": 0.08373477436102236,
        "rmse_median": 0.004715861286967993,
        "rmse_mean": 0.0060948822647333145,
        "ber_median": 15.981466293334961,
        "ber_mean": 128.62257385253906
    },
    "492": {
        "depressed": "no",
        "phq_score": "0",
        "gender": "female",
        "f0_median": 207.05298476827548,
        "f0_mean": 227.43199986516,
        "f0_range": 226.52592445654037,
        "zcr_median": 0.041015625,
        "zcr_mean": 0.05240677416134185,
        "rmse_median": 0.002684101928025484,
        "rmse_mean": 0.0037123041693121195,
        "ber_median": 91.88751220703125,
        "ber_mean": 448.75653076171875
    },
    "300": {
        "depressed": "no",
        "phq_score": "2",
        "gender": "male",
        "f0_median": 166.24757922855756,
        "f0_mean": 175.99271135526826,
        "f0_range": 172.62492069885602,
        "zcr_median": 0.06640625,
        "zcr_mean": 0.08004380491214058,
        "rmse_median": 0.007016502320766449,
        "rmse_mean": 0.00951588898897171,
        "ber_median": 29.860475540161133,
        "ber_mean": 102.8178482055664
    },
    "301": {
        "depressed": "no",
        "phq_score": "3",
        "gender": "male",
        "f0_median": 132.71517423385683,
        "f0_mean": 139.67311114803448,
        "f0_range": 164.388285302572,
        "zcr_median": 0.05859375,
        "zcr_mean": 0.08907934804313099,
        "rmse_median": 0.005840009078383446,
        "rmse_mean": 0.008715951815247536,
        "ber_median": 33.6226806640625,
        "ber_mean": 113.21559143066406
    },
    "306": {
        "depressed": "no",
        "phq_score": "0",
        "gender": "female",
        "f0_median": 227.10088581417543,
        "f0_mean": 238.7588403143975,
        "f0_range": 233.10405237298826,
        "zcr_median": 0.048828125,
        "zcr_mean": 0.05744558706070287,
        "rmse_median": 0.018271662294864655,
        "rmse_mean": 0.0230675358325243,
        "ber_median": 114.00477600097656,
        "ber_mean": 175.5620880126953
    },
    "308": {
        "depressed": "yes",
        "phq_score": "22",
        "gender": "female",
        "f0_median": 118.23577860271482,
        "f0_mean": 156.65622426260984,
        "f0_range": 220.5303400050195,
        "zcr_median": 0.0390625,
        "zcr_mean": 0.043864192292332266,
        "rmse_median": 0.01617169752717018,
        "rmse_mean": 0.017400840297341347,
        "ber_median": 158.54196166992188,
        "ber_mean": 233.09193420410156
    },
    "309": {
        "depressed": "yes",
        "phq_score": "15",
        "gender": "male",
        "f0_median": 168.1792830507429,
        "f0_mean": 169.04070836612277,
        "f0_range": 236.53212643299457,
        "zcr_median": 0.0625,
        "zcr_mean": 0.08629630091853036,
        "rmse_median": 0.018253345042467117,
        "rmse_mean": 0.019757810980081558,
        "ber_median": 28.55301284790039,
        "ber_mean": 326.4364318847656
    },
    "311": {
        "depressed": "yes",
        "phq_score": "21",
        "gender": "female",
        "f0_median": 241.99881784385852,
        "f0_mean": 259.6580260347144,
        "f0_range": 210.66513741802126,
        "zcr_median": 0.060546875,
        "zcr_mean": 0.1060178714057508,
        "rmse_median": 0.00175375840626657,
        "rmse_mean": 0.002721236553043127,
        "ber_median": 26.303936004638672,
        "ber_mean": 184.82078552246094
    },
    "314": {
        "depressed": "no",
        "phq_score": "1",
        "gender": "female",
        "f0_median": 201.15858821357068,
        "f0_mean": 218.78369493535826,
        "f0_range": 289.03376654768067,
        "zcr_median": 0.046875,
        "zcr_mean": 0.07208466453674121,
        "rmse_median": 0.003335717134177685,
        "rmse_mean": 0.004128576721996069,
        "ber_median": 54.540245056152344,
        "ber_mean": 324.357666015625
    },
    "323": {
        "depressed": "no",
        "phq_score": "1",
        "gender": "female",
        "f0_median": 236.47155720542963,
        "f0_mean": 253.9918473827606,
        "f0_range": 292.9066253066996,
        "zcr_median": 0.0546875,
        "zcr_mean": 0.06740777256389777,
        "rmse_median": 0.0017264565685763955,
        "rmse_mean": 0.0025571859441697598,
        "ber_median": 47.44326400756836,
        "ber_mean": 319.2386779785156
    },
    "329": {
        "depressed": "no",
        "phq_score": "1",
        "gender": "male",
        "f0_median": 138.99182198423372,
        "f0_mean": 142.97707226140287,
        "f0_range": 145.38666627917627,
        "zcr_median": 0.029296875,
        "zcr_mean": 0.05583566293929713,
        "rmse_median": 0.003576067276299,
        "rmse_mean": 0.004840882495045662,
        "ber_median": 104.48651123046875,
        "ber_mean": 368.6689147949219
    },
    "332": {
        "depressed": "yes",
        "phq_score": "18",
        "gender": "female",
        "f0_median": 184.46323871718783,
        "f0_mean": 185.01923043895104,
        "f0_range": 194.77612511500416,
        "zcr_median": 0.056640625,
        "zcr_mean": 0.08648974141373802,
        "rmse_median": 0.004949823021888733,
        "rmse_mean": 0.007004939019680023,
        "ber_median": 28.228939056396484,
        "ber_mean": 273.0639953613281
    },
    "334": {
        "depressed": "no",
        "phq_score": "5",
        "gender": "male",
        "f0_median": 182.34449771164336,
        "f0_mean": 190.3593405544578,
        "f0_range": 366.37351330701824,
        "zcr_median": 0.048828125,
        "zcr_mean": 0.06906449680511183,
        "rmse_median": 0.007446027360856533,
        "rmse_mean": 0.009297841228544712,
        "ber_median": 65.99104309082031,
        "ber_mean": 986.8441772460938
    },
    "337": {
        "depressed": "yes",
        "phq_score": "10",
        "gender": "female",
        "f0_median": 220.63576443274928,
        "f0_mean": 236.6983681717758,
        "f0_range": 309.8875230284922,
        "zcr_median": 0.0595703125,
        "zcr_mean": 0.09142247404153354,
        "rmse_median": 0.003429786767810583,
        "rmse_mean": 0.005006519611924887,
        "ber_median": 27.10100555419922,
        "ber_mean": 311.3037414550781
    },
    "349": {
        "depressed": "no",
        "phq_score": "5",
        "gender": "male",
        "f0_median": 145.56531828421873,
        "f0_mean": 148.3475436710378,
        "f0_range": 85.5579437204867,
        "zcr_median": 0.04296875,
        "zcr_mean": 0.08739454373003194,
        "rmse_median": 0.0032987301237881184,
        "rmse_mean": 0.00402648514136672,
        "ber_median": 45.48303985595703,
        "ber_mean": 236.95639038085938
    },
    "354": {
        "depressed": "yes",
        "phq_score": "18",
        "gender": "male",
        "f0_median": 126.72196982870621,
        "f0_mean": 126.97463480747513,
        "f0_range": 57.114375675763526,
        "zcr_median": 0.04296875,
        "zcr_mean": 0.05705870607028754,
        "rmse_median": 0.0029190639033913612,
        "rmse_mean": 0.0034318137913942337,
        "ber_median": 54.72834014892578,
        "ber_mean": 228.87290954589844
    },
    "359": {
        "depressed": "yes",
        "phq_score": "13",
        "gender": "male",
        "f0_median": 154.22108254079407,
        "f0_mean": 156.46252979150464,
        "f0_range": 145.11864287959307,
        "zcr_median": 0.0380859375,
        "zcr_mean": 0.0518950928514377,
        "rmse_median": 0.006312796846032143,
        "rmse_mean": 0.008622600696980953,
        "ber_median": 70.53369140625,
        "ber_mean": 455.5899658203125
    },
    "361": {
        "depressed": "no",
        "phq_score": "0",
        "gender": "male",
        "f0_median": 174.11011265922482,
        "f0_mean": 177.43718496520557,
        "f0_range": 114.5427551119323,
        "zcr_median": 0.0546875,
        "zcr_mean": 0.10554675019968052,
        "rmse_median": 0.0023183301091194153,
        "rmse_mean": 0.003094683401286602,
        "ber_median": 30.02431869506836,
        "ber_mean": 115.8359146118164
    },
    "365": {
        "depressed": "yes",
        "phq_score": "12",
        "gender": "male",
        "f0_median": 110.95694720678449,
        "f0_mean": 111.54666689054868,
        "f0_range": 50.124700637162746,
        "zcr_median": 0.037109375,
        "zcr_mean": 0.06456856529552715,
        "rmse_median": 0.0035490752197802067,
        "rmse_mean": 0.003703178372234106,
        "ber_median": 145.25253295898438,
        "ber_mean": 517.0824584960938
    },
    "373": {
        "depressed": "no",
        "phq_score": "9",
        "gender": "male",
        "f0_median": 100.0,
        "f0_mean": 101.22273231389045,
        "f0_range": 46.16151813324254,
        "zcr_median": 0.044921875,
        "zcr_mean": 0.0746617911341853,
        "rmse_median": 0.004086783155798912,
        "rmse_mean": 0.004828746896237135,
        "ber_median": 119.58201599121094,
        "ber_mean": 656.5505981445312
    },
    "378": {
        "depressed": "no",
        "phq_score": "1",
        "gender": "female",
        "f0_median": 256.3888163841458,
        "f0_mean": 263.6386927162338,
        "f0_range": 374.64996426999824,
        "zcr_median": 0.0625,
        "zcr_mean": 0.08989991014376997,
        "rmse_median": 0.003671842161566019,
        "rmse_mean": 0.004826168995350599,
        "ber_median": 19.117572784423828,
        "ber_mean": 287.52020263671875
    },
    "384": {
        "depressed": "yes",
        "phq_score": "15",
        "gender": "male",
        "f0_median": 152.4497023255762,
        "f0_mean": 162.07508202279902,
        "f0_range": 392.6332625226106,
        "zcr_median": 0.048828125,
        "zcr_mean": 0.08170676916932908,
        "rmse_median": 0.005276123993098736,
        "rmse_mean": 0.008573109284043312,
        "ber_median": 37.59904479980469,
        "ber_mean": 1568.95556640625
    },
    "396": {
        "depressed": "no",
        "phq_score": "5",
        "gender": "male",
        "f0_median": 116.20455869578394,
        "f0_mean": 119.62420606822039,
        "f0_range": 334.0085812927998,
        "zcr_median": 0.056640625,
        "zcr_mean": 0.0886675069888179,
        "rmse_median": 0.004039249382913113,
        "rmse_mean": 0.004337890073657036,
        "ber_median": 49.245941162109375,
        "ber_mean": 205.28353881835938
    },
    "399": {
        "depressed": "no",
        "phq_score": "7",
        "gender": "female",
        "f0_median": 236.47155720542963,
        "f0_mean": 237.43485793867197,
        "f0_range": 243.82778882713797,
        "zcr_median": 0.046875,
        "zcr_mean": 0.05872479033546326,
        "rmse_median": 0.0035366241354495287,
        "rmse_mean": 0.003305121324956417,
        "ber_median": 87.91155242919922,
        "ber_mean": 508.46905517578125
    },
    "405": {
        "depressed": "yes",
        "phq_score": "17",
        "gender": "female",
        "f0_median": 260.87041395311286,
        "f0_mean": 260.05487711847496,
        "f0_range": 181.2703529443089,
        "zcr_median": 0.046875,
        "zcr_mean": 0.08024972543929712,
        "rmse_median": 0.009103596210479736,
        "rmse_mean": 0.011597509495913982,
        "ber_median": 68.76527404785156,
        "ber_mean": 1209.6707763671875
    },
    "407": {
        "depressed": "no",
        "phq_score": "3",
        "gender": "male",
        "f0_median": 192.07458901020084,
        "f0_mean": 199.9333936984085,
        "f0_range": 252.77079430028047,
        "zcr_median": 0.04296875,
        "zcr_mean": 0.06412552416134186,
        "rmse_median": 0.00674315495416522,
        "rmse_mean": 0.01008015125989914,
        "ber_median": 110.06559753417969,
        "ber_mean": 680.3721923828125
    },
    "408": {
        "depressed": "no",
        "phq_score": "0",
        "gender": "female",
        "f0_median": 259.3679109302019,
        "f0_mean": 224.95957381755647,
        "f0_range": 369.3340743920942,
        "zcr_median": 0.05859375,
        "zcr_mean": 0.08839606629392971,
        "rmse_median": 0.0012203213991597295,
        "rmse_mean": 0.001386959571391344,
        "ber_median": 39.503639221191406,
        "ber_mean": 108.3604507446289
    },
    "410": {
        "depressed": "yes",
        "phq_score": "12",
        "gender": "female",
        "f0_median": 228.41646786215435,
        "f0_mean": 230.721388178824,
        "f0_range": 96.82424833771628,
        "zcr_median": 0.052734375,
        "zcr_mean": 0.08152580870607029,
        "rmse_median": 0.0012755799107253551,
        "rmse_mean": 0.0018142327899113297,
        "ber_median": 58.39656066894531,
        "ber_mean": 172.95306396484375
    },
    "411": {
        "depressed": "no",
        "phq_score": "0",
        "gender": "female",
        "f0_median": 250.53288772482563,
        "f0_mean": 249.98339921624384,
        "f0_range": 358.8719253472063,
        "zcr_median": 0.056640625,
        "zcr_mean": 0.14185428314696485,
        "rmse_median": 0.0077273123897612095,
        "rmse_mean": 0.008758791722357273,
        "ber_median": 66.01240539550781,
        "ber_mean": 522.7080688476562
    },
    "421": {
        "depressed": "yes",
        "phq_score": "10",
        "gender": "female",
        "f0_median": 277.98364396846745,
        "f0_mean": 285.5156125018064,
        "f0_range": 347.7260290158432,
        "zcr_median": 0.048828125,
        "zcr_mean": 0.09506976337859425,
        "rmse_median": 0.003735222155228257,
        "rmse_mean": 0.003707694821059704,
        "ber_median": 77.79399108886719,
        "ber_mean": 754.8431396484375
    },
    "424": {
        "depressed": "no",
        "phq_score": "3",
        "gender": "female",
        "f0_median": 239.21922434748075,
        "f0_mean": 243.4055204331122,
        "f0_range": 288.94638725605046,
        "zcr_median": 0.052734375,
        "zcr_mean": 0.061542157547923325,
        "rmse_median": 0.012884410098195076,
        "rmse_mean": 0.019142858684062958,
        "ber_median": 81.44194793701172,
        "ber_mean": 1384.635986328125
    },
    "431": {
        "depressed": "no",
        "phq_score": "2",
        "gender": "female",
        "f0_median": 225.14264531155038,
        "f0_mean": 240.58164863240228,
        "f0_range": 170.97207875283735,
        "zcr_median": 0.046875,
        "zcr_mean": 0.06131439696485623,
        "rmse_median": 0.0017018832731992006,
        "rmse_mean": 0.0020248512737452984,
        "ber_median": 80.90443420410156,
        "ber_mean": 263.11724853515625
    },
    "432": {
        "depressed": "no",
        "phq_score": "1",
        "gender": "male",
        "f0_median": 121.7003513670591,
        "f0_mean": 123.87816924446925,
        "f0_range": 65.46267244743326,
        "zcr_median": 0.029296875,
        "zcr_mean": 0.04930860623003195,
        "rmse_median": 0.002657618373632431,
        "rmse_mean": 0.003332932945340872,
        "ber_median": 236.65667724609375,
        "ber_mean": 760.135009765625
    },
    "435": {
        "depressed": "no",
        "phq_score": "8",
        "gender": "female",
        "f0_median": 192.07458901020084,
        "f0_mean": 208.14800817852742,
        "f0_range": 322.8753163233745,
        "zcr_median": 0.041015625,
        "zcr_mean": 0.05887767072683706,
        "rmse_median": 0.002368493005633354,
        "rmse_mean": 0.003097769571468234,
        "ber_median": 122.60809326171875,
        "ber_mean": 558.8714599609375
    },
    "438": {
        "depressed": "no",
        "phq_score": "2",
        "gender": "female",
        "f0_median": 227.10088581417543,
        "f0_mean": 198.10511562002782,
        "f0_range": 242.47260568746339,
        "zcr_median": 0.048828125,
        "zcr_mean": 0.06865889576677316,
        "rmse_median": 0.002905659144744277,
        "rmse_mean": 0.0030086669139564037,
        "ber_median": 55.4002685546875,
        "ber_mean": 278.3556213378906
    },
    "442": {
        "depressed": "no",
        "phq_score": "6",
        "gender": "male",
        "f0_median": 135.034994616819,
        "f0_mean": 135.70594091807953,
        "f0_range": 92.65827228177619,
        "zcr_median": 0.037109375,
        "zcr_mean": 0.0708460213658147,
        "rmse_median": 0.004763626493513584,
        "rmse_mean": 0.005887205246835947,
        "ber_median": 124.27488708496094,
        "ber_mean": 543.8720092773438
    },
    "450": {
        "depressed": "no",
        "phq_score": "9",
        "gender": "female",
        "f0_median": 184.46323871718783,
        "f0_mean": 187.67898912867886,
        "f0_range": 214.8436801943009,
        "zcr_median": 0.046875,
        "zcr_mean": 0.07889252196485623,
        "rmse_median": 0.004744639620184898,
        "rmse_mean": 0.006625115871429443,
        "ber_median": 77.61820220947266,
        "ber_mean": 637.4590454101562
    },
    "452": {
        "depressed": "no",
        "phq_score": "1",
        "gender": "female",
        "f0_median": 270.06998923363795,
        "f0_mean": 285.8060120805514,
        "f0_range": 226.81845977932534,
        "zcr_median": 0.06640625,
        "zcr_mean": 0.10088857827476039,
        "rmse_median": 0.0026094643399119377,
        "rmse_mean": 0.003667028620839119,
        "ber_median": 34.93638610839844,
        "ber_mean": 175.7373809814453
    },
    "453": {
        "depressed": "yes",
        "phq_score": "17",
        "gender": "male",
        "f0_median": 128.1944081920729,
        "f0_mean": 148.315607501606,
        "f0_range": 376.91586335976274,
        "zcr_median": 0.037109375,
        "zcr_mean": 0.05374837759584664,
        "rmse_median": 0.0029078954830765724,
        "rmse_mean": 0.004065690562129021,
        "ber_median": 79.8517074584961,
        "ber_mean": 541.6917114257812
    },
    "461": {
        "depressed": "yes",
        "phq_score": "17",
        "gender": "male",
        "f0_median": 147.25670581005258,
        "f0_mean": 148.38412578866917,
        "f0_range": 135.09300909400008,
        "zcr_median": 0.052734375,
        "zcr_mean": 0.09732240914536741,
        "rmse_median": 0.002825502771884203,
        "rmse_mean": 0.0033584630582481623,
        "ber_median": 37.66139221191406,
        "ber_mean": 222.59335327148438
    },
    "462": {
        "depressed": "no",
        "phq_score": "9",
        "gender": "female",
        "f0_median": 204.67477839935495,
        "f0_mean": 229.1380031787823,
        "f0_range": 282.1190914695276,
        "zcr_median": 0.0625,
        "zcr_mean": 0.09978721545527157,
        "rmse_median": 0.004365603439509869,
        "rmse_mean": 0.004466529935598373,
        "ber_median": 33.888614654541016,
        "ber_mean": 160.87469482421875
    },
    "465": {
        "depressed": "no",
        "phq_score": "2",
        "gender": "male",
        "f0_median": 150.69866814745757,
        "f0_mean": 158.35961027261962,
        "f0_range": 127.19614403833423,
        "zcr_median": 0.0537109375,
        "zcr_mean": 0.06796001397763578,
        "rmse_median": 0.011854131706058979,
        "rmse_mean": 0.01751423254609108,
        "ber_median": 40.1441764831543,
        "ber_mean": 215.37841796875
    },
    "466": {
        "depressed": "no",
        "phq_score": "9",
        "gender": "female",
        "f0_median": 240.60500721642333,
        "f0_mean": 247.43571168798556,
        "f0_range": 129.74650491604885,
        "zcr_median": 0.046875,
        "zcr_mean": 0.06555760782747604,
        "rmse_median": 0.00255102408118546,
        "rmse_mean": 0.0030353774782270193,
        "ber_median": 60.311676025390625,
        "ber_mean": 269.0650939941406
    },
    "467": {
        "depressed": "no",
        "phq_score": "0",
        "gender": "male",
        "f0_median": 104.12621525348065,
        "f0_mean": 109.18587117835477,
        "f0_range": 308.8519520405441,
        "zcr_median": 0.046875,
        "zcr_mean": 0.06794129392971246,
        "rmse_median": 0.005262014456093311,
        "rmse_mean": 0.005881005432456732,
        "ber_median": 53.83489990234375,
        "ber_mean": 291.6711120605469
    },
    "469": {
        "depressed": "no",
        "phq_score": "3",
        "gender": "female",
        "f0_median": 241.99881784385852,
        "f0_mean": 255.25983586437573,
        "f0_range": 222.35352941920056,
        "zcr_median": 0.0546875,
        "zcr_mean": 0.0848392571884984,
        "rmse_median": 0.004746794700622559,
        "rmse_mean": 0.005447033327072859,
        "ber_median": 65.29063415527344,
        "ber_mean": 469.1449279785156
    },
    "470": {
        "depressed": "no",
        "phq_score": "3",
        "gender": "female",
        "f0_median": 273.20805135087915,
        "f0_mean": 270.96364519939664,
        "f0_range": 318.75953516159956,
        "zcr_median": 0.0517578125,
        "zcr_mean": 0.0683281749201278,
        "rmse_median": 0.017669567838311195,
        "rmse_mean": 0.019713617861270905,
        "ber_median": 50.676353454589844,
        "ber_mean": 860.0358276367188
    },
    "480": {
        "depressed": "no",
        "phq_score": "1",
        "gender": "male",
        "f0_median": 119.60961217374037,
        "f0_mean": 123.3810179638361,
        "f0_range": 147.51882002701365,
        "zcr_median": 0.046875,
        "zcr_mean": 0.06950129792332269,
        "rmse_median": 0.010340659879148006,
        "rmse_mean": 0.010902074165642262,
        "ber_median": 28.81174087524414,
        "ber_mean": 151.19383239746094
    },
    "481": {
        "depressed": "no",
        "phq_score": "7",
        "gender": "male",
        "f0_median": 179.21192838239048,
        "f0_mean": 177.3336857708347,
        "f0_range": 152.66556824686646,
        "zcr_median": 0.05078125,
        "zcr_mean": 0.06669329073482429,
        "rmse_median": 0.006337668746709824,
        "rmse_mean": 0.0079369330778718,
        "ber_median": 34.037574768066406,
        "ber_mean": 175.40806579589844
    },
    "303": {
        "depressed": "no",
        "phq_score": "0",
        "gender": "female",
        "f0_median": 291.13063656843747,
        "f0_mean": 292.8301344581832,
        "f0_range": 284.63143641506326,
        "zcr_median": 0.056640625,
        "zcr_mean": 0.06669953075079872,
        "rmse_median": 0.006371396128088236,
        "rmse_mean": 0.01014945562928915,
        "ber_median": 52.613800048828125,
        "ber_mean": 151.88702392578125
    },
    "304": {
        "depressed": "no",
        "phq_score": "6",
        "gender": "female",
        "f0_median": 294.5134116201051,
        "f0_mean": 313.99015233398126,
        "f0_range": 325.5370530734697,
        "zcr_median": 0.056640625,
        "zcr_mean": 0.05895879093450479,
        "rmse_median": 0.0031061344780027866,
        "rmse_mean": 0.004142044577747583,
        "ber_median": 51.154457092285156,
        "ber_mean": 107.77273559570312
    },
    "305": {
        "depressed": "no",
        "phq_score": "7",
        "gender": "male",
        "f0_median": 152.4497023255762,
        "f0_mean": 147.84844422240866,
        "f0_range": 95.47156338265796,
        "zcr_median": 0.044921875,
        "zcr_mean": 0.04732428115015974,
        "rmse_median": 0.03851769119501114,
        "rmse_mean": 0.05172877386212349,
        "ber_median": 139.28195190429688,
        "ber_mean": 254.3452911376953
    },
    "310": {
        "depressed": "no",
        "phq_score": "4",
        "gender": "male",
        "f0_median": 100.57929410678534,
        "f0_mean": 110.2330655080919,
        "f0_range": 378.2645786825216,
        "zcr_median": 0.048828125,
        "zcr_mean": 0.062147439097444086,
        "rmse_median": 0.005912119522690773,
        "rmse_mean": 0.008865941315889359,
        "ber_median": 32.04853820800781,
        "ber_mean": 1186.102783203125
    },
    "312": {
        "depressed": "no",
        "phq_score": "2",
        "gender": "male",
        "f0_median": 125.99210498948732,
        "f0_mean": 136.2676117363131,
        "f0_range": 405.90410923735215,
        "zcr_median": 0.033203125,
        "zcr_mean": 0.0406349840255591,
        "rmse_median": 0.014432496391236782,
        "rmse_mean": 0.019025452435016632,
        "ber_median": 233.7853240966797,
        "ber_mean": 3416.98486328125
    },
    "313": {
        "depressed": "no",
        "phq_score": "7",
        "gender": "male",
        "f0_median": 132.71517423385683,
        "f0_mean": 136.9413567077271,
        "f0_range": 327.06329493442144,
        "zcr_median": 0.05078125,
        "zcr_mean": 0.0928046375798722,
        "rmse_median": 0.0048559908755123615,
        "rmse_mean": 0.0063916100189089775,
        "ber_median": 27.850154876708984,
        "ber_mean": 246.14781188964844
    },
    "315": {
        "depressed": "no",
        "phq_score": "2",
        "gender": "male",
        "f0_median": 148.1097552286564,
        "f0_mean": 150.11710641785416,
        "f0_range": 158.25705256031674,
        "zcr_median": 0.0390625,
        "zcr_mean": 0.042135707867412144,
        "rmse_median": 0.013153976760804653,
        "rmse_mean": 0.021153761073946953,
        "ber_median": 228.74127197265625,
        "ber_mean": 12087.4501953125
    },
    "316": {
        "depressed": "no",
        "phq_score": "6",
        "gender": "male",
        "f0_median": 129.68395546510095,
        "f0_mean": 133.7003794971805,
        "f0_range": 337.8814793912084,
        "zcr_median": 0.033203125,
        "zcr_mean": 0.05034132887380192,
        "rmse_median": 0.004838136490434408,
        "rmse_mean": 0.006054495461285114,
        "ber_median": 89.74310302734375,
        "ber_mean": 1266.2288818359375
    },
    "317": {
        "depressed": "no",
        "phq_score": "8",
        "gender": "male",
        "f0_median": 120.99940892192926,
        "f0_mean": 125.40038957842543,
        "f0_range": 74.21932363123777,
        "zcr_median": 0.048828125,
        "zcr_mean": 0.10730955471246006,
        "rmse_median": 0.004492701962590218,
        "rmse_mean": 0.005350111518055201,
        "ber_median": 41.83561706542969,
        "ber_mean": 276.26226806640625
    },
    "318": {
        "depressed": "no",
        "phq_score": "3",
        "gender": "male",
        "f0_median": 116.87772485612456,
        "f0_mean": 116.96556931951329,
        "f0_range": 57.3397019004677,
        "zcr_median": 0.0390625,
        "zcr_mean": 0.05332093650159744,
        "rmse_median": 0.00930821429938078,
        "rmse_mean": 0.012443320825695992,
        "ber_median": 76.62788391113281,
        "ber_mean": 473.7345275878906
    },
    "319": {
        "depressed": "yes",
        "phq_score": "13",
        "gender": "male",
        "f0_median": 116.20455869578394,
        "f0_mean": 118.27470241605184,
        "f0_range": 74.45977703039598,
        "zcr_median": 0.048828125,
        "zcr_mean": 0.07602835463258786,
        "rmse_median": 0.0023076923098415136,
        "rmse_mean": 0.0025542257353663445,
        "ber_median": 29.11774444580078,
        "ber_mean": 149.5360107421875
    },
    "320": {
        "depressed": "yes",
        "phq_score": "11",
        "gender": "female",
        "f0_median": 263.9015821545788,
        "f0_mean": 270.7961343851761,
        "f0_range": 283.6082569908876,
        "zcr_median": 0.0390625,
        "zcr_mean": 0.05231317392172524,
        "rmse_median": 0.0021912958472967148,
        "rmse_mean": 0.00601808400824666,
        "ber_median": 128.18588256835938,
        "ber_mean": 424.8820495605469
    },
    "321": {
        "depressed": "yes",
        "phq_score": "20",
        "gender": "female",
        "f0_median": 282.842712474619,
        "f0_mean": 288.924115785245,
        "f0_range": 202.7764053549877,
        "zcr_median": 0.0556640625,
        "zcr_mean": 0.07322970746805112,
        "rmse_median": 0.00032235696562565863,
        "rmse_mean": 0.0009745651041157544,
        "ber_median": 34.15306091308594,
        "ber_mean": 113.44525909423828
    },
    "322": {
        "depressed": "no",
        "phq_score": "5",
        "gender": "male",
        "f0_median": 148.5387507704633,
        "f0_mean": 151.2956720371424,
        "f0_range": 83.46671957463808,
        "zcr_median": 0.0390625,
        "zcr_mean": 0.061333117012779555,
        "rmse_median": 0.005166565999388695,
        "rmse_mean": 0.005457509309053421,
        "ber_median": 107.23130798339844,
        "ber_mean": 733.3748779296875
    },
    "324": {
        "depressed": "no",
        "phq_score": "5",
        "gender": "male",
        "f0_median": 128.9370308439579,
        "f0_mean": 128.85276875753482,
        "f0_range": 80.65698555708761,
        "zcr_median": 0.048828125,
        "zcr_mean": 0.07304874700479233,
        "rmse_median": 0.006620696745812893,
        "rmse_mean": 0.00723440432921052,
        "ber_median": 45.345115661621094,
        "ber_mean": 257.6343994140625
    },
    "325": {
        "depressed": "yes",
        "phq_score": "10",
        "gender": "female",
        "f0_median": 241.99881784385852,
        "f0_mean": 249.16858497910957,
        "f0_range": 256.83869223353105,
        "zcr_median": 0.05859375,
        "zcr_mean": 0.09184679512779553,
        "rmse_median": 0.006174443289637566,
        "rmse_mean": 0.006645001471042633,
        "ber_median": 32.42608642578125,
        "ber_mean": 202.25987243652344
    },
    "326": {
        "depressed": "no",
        "phq_score": "2",
        "gender": "male",
        "f0_median": 141.8309790285188,
        "f0_mean": 155.05287338017595,
        "f0_range": 171.58215730638005,
        "zcr_median": 0.03515625,
        "zcr_mean": 0.05830982927316294,
        "rmse_median": 0.007870637811720371,
        "rmse_mean": 0.009313543327152729,
        "ber_median": 106.76498413085938,
        "ber_mean": 436.59490966796875
    },
    "327": {
        "depressed": "no",
        "phq_score": "4",
        "gender": "female",
        "f0_median": 253.44393965741244,
        "f0_mean": 255.8316424587226,
        "f0_range": 258.608595218001,
        "zcr_median": 0.0625,
        "zcr_mean": 0.08512317791533547,
        "rmse_median": 0.003490666626021266,
        "rmse_mean": 0.004699208308011293,
        "ber_median": 33.95944595336914,
        "ber_mean": 203.08612060546875
    },
    "328": {
        "depressed": "no",
        "phq_score": "4",
        "gender": "male",
        "f0_median": 185.5318233882619,
        "f0_mean": 207.27401113852778,
        "f0_range": 275.09230652068356,
        "zcr_median": 0.05859375,
        "zcr_mean": 0.09089831269968052,
        "rmse_median": 0.006539911963045597,
        "rmse_mean": 0.010373051278293133,
        "ber_median": 31.946422576904297,
        "ber_mean": 372.2268981933594
    },
    "330": {
        "depressed": "yes",
        "phq_score": "12",
        "gender": "male",
        "f0_median": 116.20455869578394,
        "f0_mean": 119.74578092840798,
        "f0_range": 73.96581102115984,
        "zcr_median": 0.056640625,
        "zcr_mean": 0.13155825678913738,
        "rmse_median": 0.0019856784492731094,
        "rmse_mean": 0.004539623390883207,
        "ber_median": 19.17089080810547,
        "ber_mean": 74.80719757080078
    },
    "333": {
        "depressed": "no",
        "phq_score": "5",
        "gender": "male",
        "f0_median": 138.99182198423372,
        "f0_mean": 139.35133035592435,
        "f0_range": 59.583452593949744,
        "zcr_median": 0.044921875,
        "zcr_mean": 0.0591428714057508,
        "rmse_median": 0.006714632734656334,
        "rmse_mean": 0.0071669104509055614,
        "ber_median": 51.94510269165039,
        "ber_mean": 362.1664733886719
    },
    "336": {
        "depressed": "no",
        "phq_score": "7",
        "gender": "male",
        "f0_median": 121.34988014449418,
        "f0_mean": 134.9352248083646,
        "f0_range": 124.2902526086737,
        "zcr_median": 0.046875,
        "zcr_mean": 0.08185028953674121,
        "rmse_median": 0.005007626488804817,
        "rmse_mean": 0.006233230698853731,
        "ber_median": 58.69212341308594,
        "ber_mean": 432.4047546386719
    },
    "338": {
        "depressed": "yes",
        "phq_score": "15",
        "gender": "female",
        "f0_median": 232.40911739156792,
        "f0_mean": 257.5377603207254,
        "f0_range": 314.78436421908594,
        "zcr_median": 0.0703125,
        "zcr_mean": 0.09218063598242812,
        "rmse_median": 0.01055069174617529,
        "rmse_mean": 0.01593255251646042,
        "ber_median": 20.06500816345215,
        "ber_mean": 245.79835510253906
    },
    "339": {
        "depressed": "yes",
        "phq_score": "11",
        "gender": "male",
        "f0_median": 98.2820598545251,
        "f0_mean": 100.35031363324686,
        "f0_range": 54.86770013669522,
        "zcr_median": 0.041015625,
        "zcr_mean": 0.059464232228434506,
        "rmse_median": 0.00538245402276516,
        "rmse_mean": 0.0061198025941848755,
        "ber_median": 79.51889038085938,
        "ber_mean": 333.3652038574219
    },
    "340": {
        "depressed": "no",
        "phq_score": "1",
        "gender": "male",
        "f0_median": 114.86983549970348,
        "f0_mean": 117.39270615430704,
        "f0_range": 87.55642280899363,
        "zcr_median": 0.044921875,
        "zcr_mean": 0.06385720347444089,
        "rmse_median": 0.004999942611902952,
        "rmse_mean": 0.00716787576675415,
        "ber_median": 51.50751495361328,
        "ber_mean": 204.9770050048828
    },
    "341": {
        "depressed": "no",
        "phq_score": "7",
        "gender": "female",
        "f0_median": 244.1057056975246,
        "f0_mean": 247.86166722814397,
        "f0_range": 94.77305006206106,
        "zcr_median": 0.048828125,
        "zcr_mean": 0.06299296126198083,
        "rmse_median": 0.0007970344740897417,
        "rmse_mean": 0.004551928490400314,
        "ber_median": 55.571781158447266,
        "ber_mean": 185.9720916748047
    },
    "343": {
        "depressed": "no",
        "phq_score": "9",
        "gender": "male",
        "f0_median": 123.11444133449163,
        "f0_mean": 128.2610287322377,
        "f0_range": 79.54630147535345,
        "zcr_median": 0.044921875,
        "zcr_mean": 0.08720734325079872,
        "rmse_median": 0.0034307094756513834,
        "rmse_mean": 0.005217045079916716,
        "ber_median": 76.16584014892578,
        "ber_mean": 295.29791259765625
    },
    "344": {
        "depressed": "yes",
        "phq_score": "11",
        "gender": "male",
        "f0_median": 109.68249796946259,
        "f0_mean": 115.61518022534261,
        "f0_range": 115.7702319597702,
        "zcr_median": 0.052734375,
        "zcr_mean": 0.06895841653354633,
        "rmse_median": 0.02112419158220291,
        "rmse_mean": 0.030708273872733116,
        "ber_median": 23.750995635986328,
        "ber_mean": 910.3206787109375
    },
    "345": {
        "depressed": "yes",
        "phq_score": "15",
        "gender": "female",
        "f0_median": 266.96797083400685,
        "f0_mean": 295.62932646124415,
        "f0_range": 369.3189137136504,
        "zcr_median": 0.076171875,
        "zcr_mean": 0.10667307308306709,
        "rmse_median": 0.003908814396709204,
        "rmse_mean": 0.006476730573922396,
        "ber_median": 12.864383697509766,
        "ber_mean": 84.64727783203125
    },
    "347": {
        "depressed": "yes",
        "phq_score": "16",
        "gender": "male",
        "f0_median": 135.81724438273213,
        "f0_mean": 142.11053898980606,
        "f0_range": 154.0715303533937,
        "zcr_median": 0.046875,
        "zcr_mean": 0.06459352535942492,
        "rmse_median": 0.004648396745324135,
        "rmse_mean": 0.005548419896513224,
        "ber_median": 49.05647277832031,
        "ber_mean": 208.79173278808594
    },
    "348": {
        "depressed": "yes",
        "phq_score": "20",
        "gender": "female",
        "f0_median": 235.10958125672175,
        "f0_mean": 239.64703832624411,
        "f0_range": 197.08002189549327,
        "zcr_median": 0.0546875,
        "zcr_mean": 0.09042095147763578,
        "rmse_median": 0.00651120487600565,
        "rmse_mean": 0.007831425406038761,
        "ber_median": 40.7006721496582,
        "ber_mean": 196.406494140625
    },
    "350": {
        "depressed": "yes",
        "phq_score": "11",
        "gender": "female",
        "f0_median": 204.67477839935495,
        "f0_mean": 209.66439106998732,
        "f0_range": 244.6581617810187,
        "zcr_median": 0.0703125,
        "zcr_mean": 0.08867062699680511,
        "rmse_median": 0.002758740447461605,
        "rmse_mean": 0.003360813483595848,
        "ber_median": 22.418506622314453,
        "ber_mean": 113.7623291015625
    },
    "351": {
        "depressed": "yes",
        "phq_score": "14",
        "gender": "female",
        "f0_median": 249.08992447176465,
        "f0_mean": 249.88100726500983,
        "f0_range": 192.35589871847156,
        "zcr_median": 0.0439453125,
        "zcr_mean": 0.0648056859025559,
        "rmse_median": 0.0045688571408391,
        "rmse_mean": 0.0050824047066271305,
        "ber_median": 55.317771911621094,
        "ber_mean": 327.0226745605469
    },
    "352": {
        "depressed": "yes",
        "phq_score": "10",
        "gender": "female",
        "f0_median": 256.3888163841458,
        "f0_mean": 259.839517780331,
        "f0_range": 372.0666266935012,
        "zcr_median": 0.0556640625,
        "zcr_mean": 0.07810003993610223,
        "rmse_median": 0.007147379219532013,
        "rmse_mean": 0.009527902118861675,
        "ber_median": 26.937850952148438,
        "ber_mean": 379.55975341796875
    },
    "353": {
        "depressed": "yes",
        "phq_score": "11",
        "gender": "female",
        "f0_median": 210.67220719096719,
        "f0_mean": 210.1779989690178,
        "f0_range": 386.389458310245,
        "zcr_median": 0.0703125,
        "zcr_mean": 0.10118809904153354,
        "rmse_median": 0.006417808588594198,
        "rmse_mean": 0.00787867046892643,
        "ber_median": 16.484249114990234,
        "ber_mean": 190.0026397705078
    },
    "355": {
        "depressed": "yes",
        "phq_score": "10",
        "gender": "male",
        "f0_median": 172.11028744886602,
        "f0_mean": 176.4512603266426,
        "f0_range": 101.38658390935367,
        "zcr_median": 0.03125,
        "zcr_mean": 0.06825641473642173,
        "rmse_median": 0.006937154568731785,
        "rmse_mean": 0.00715128006413579,
        "ber_median": 122.59257507324219,
        "ber_mean": 544.4124145507812
    },
    "356": {
        "depressed": "yes",
        "phq_score": "10",
        "gender": "male",
        "f0_median": 146.40856959456255,
        "f0_mean": 148.6105900582516,
        "f0_range": 116.78300359780079,
        "zcr_median": 0.04296875,
        "zcr_mean": 0.09283271765175719,
        "rmse_median": 0.003383287228643894,
        "rmse_mean": 0.0043279509991407394,
        "ber_median": 53.59410858154297,
        "ber_mean": 233.53651428222656
    },
    "357": {
        "depressed": "no",
        "phq_score": "7",
        "gender": "male",
        "f0_median": 149.83070768766817,
        "f0_mean": 166.46574766575802,
        "f0_range": 335.15557871204163,
        "zcr_median": 0.048828125,
        "zcr_mean": 0.06859337559904154,
        "rmse_median": 0.005744761321693659,
        "rmse_mean": 0.0081029636785388,
        "ber_median": 39.06316375732422,
        "ber_mean": 185.5935821533203
    },
    "358": {
        "depressed": "no",
        "phq_score": "7",
        "gender": "male",
        "f0_median": 161.5148333600084,
        "f0_mean": 198.6675942907022,
        "f0_range": 373.25096256114864,
        "zcr_median": 0.056640625,
        "zcr_mean": 0.08917606829073482,
        "rmse_median": 0.0033373753540217876,
        "rmse_mean": 0.009644914418458939,
        "ber_median": 26.367612838745117,
        "ber_mean": 304.06134033203125
    },
    "360": {
        "depressed": "no",
        "phq_score": "4",
        "gender": "female",
        "f0_median": 270.06998923363795,
        "f0_mean": 270.547105627676,
        "f0_range": 132.62378870987857,
        "zcr_median": 0.048828125,
        "zcr_mean": 0.0797723642172524,
        "rmse_median": 0.00762148667126894,
        "rmse_mean": 0.008281420916318893,
        "ber_median": 92.67146301269531,
        "ber_mean": 695.6344604492188
    },
    "362": {
        "depressed": "yes",
        "phq_score": "20",
        "gender": "female",
        "f0_median": 241.99881784385852,
        "f0_mean": 233.6704098980754,
        "f0_range": 367.20686665385733,
        "zcr_median": 0.041015625,
        "zcr_mean": 0.059174071485623,
        "rmse_median": 0.0006924787303432822,
        "rmse_mean": 0.002879234729334712,
        "ber_median": 66.05207824707031,
        "ber_mean": 201.24417114257812
    },
    "363": {
        "depressed": "no",
        "phq_score": "0",
        "gender": "male",
        "f0_median": 145.56531828421873,
        "f0_mean": 147.3615098542711,
        "f0_range": 85.79176606892285,
        "zcr_median": 0.04296875,
        "zcr_mean": 0.06116463658146965,
        "rmse_median": 0.0042745694518089294,
        "rmse_mean": 0.004732209723442793,
        "ber_median": 49.51878356933594,
        "ber_mean": 433.10491943359375
    },
    "364": {
        "depressed": "no",
        "phq_score": "0",
        "gender": "male",
        "f0_median": 128.1944081920729,
        "f0_mean": 140.20785309898483,
        "f0_range": 253.14506361075203,
        "zcr_median": 0.03125,
        "zcr_mean": 0.05701814596645367,
        "rmse_median": 0.004861366003751755,
        "rmse_mean": 0.007037734147161245,
        "ber_median": 89.02191162109375,
        "ber_mean": 556.8131103515625
    },
    "366": {
        "depressed": "no",
        "phq_score": "0",
        "gender": "male",
        "f0_median": 129.68395546510095,
        "f0_mean": 154.73058712613505,
        "f0_range": 348.60494561676734,
        "zcr_median": 0.0390625,
        "zcr_mean": 0.0580446285942492,
        "rmse_median": 0.003528004977852106,
        "rmse_mean": 0.004715127870440483,
        "ber_median": 58.46836853027344,
        "ber_mean": 514.7147827148438
    },
    "368": {
        "depressed": "no",
        "phq_score": "7",
        "gender": "male",
        "f0_median": 221.27482942315913,
        "f0_mean": 238.09661234767225,
        "f0_range": 375.83173124527417,
        "zcr_median": 0.056640625,
        "zcr_mean": 0.07122978234824281,
        "rmse_median": 0.006992028560489416,
        "rmse_mean": 0.008897766470909119,
        "ber_median": 44.329750061035156,
        "ber_mean": 209.1040496826172
    },
    "369": {
        "depressed": "no",
        "phq_score": "0",
        "gender": "female",
        "f0_median": 270.06998923363795,
        "f0_mean": 288.091827754481,
        "f0_range": 240.22718433534027,
        "zcr_median": 0.04296875,
        "zcr_mean": 0.0823214107428115,
        "rmse_median": 0.0060083880089223385,
        "rmse_mean": 0.007970328442752361,
        "ber_median": 98.05731201171875,
        "ber_mean": 954.860595703125
    },
    "370": {
        "depressed": "no",
        "phq_score": "0",
        "gender": "male",
        "f0_median": 143.06459324352582,
        "f0_mean": 149.63160676221943,
        "f0_range": 181.44813859897488,
        "zcr_median": 0.046875,
        "zcr_mean": 0.05786678813897764,
        "rmse_median": 0.009621826000511646,
        "rmse_mean": 0.013616092503070831,
        "ber_median": 40.902610778808594,
        "ber_mean": 233.94786071777344
    },
    "371": {
        "depressed": "no",
        "phq_score": "9",
        "gender": "male",
        "f0_median": 131.57080076051716,
        "f0_mean": 132.3519183201161,
        "f0_range": 84.95252928147656,
        "zcr_median": 0.037109375,
        "zcr_mean": 0.07104570187699681,
        "rmse_median": 0.009949205443263054,
        "rmse_mean": 0.011350116692483425,
        "ber_median": 122.52555847167969,
        "ber_mean": 414.6238098144531
    },
    "372": {
        "depressed": "yes",
        "phq_score": "13",
        "gender": "female",
        "f0_median": 301.3973362949152,
        "f0_mean": 300.4550276252841,
        "f0_range": 361.42700912978916,
        "zcr_median": 0.052734375,
        "zcr_mean": 0.06325192192492013,
        "rmse_median": 0.005464843474328518,
        "rmse_mean": 0.009712482802569866,
        "ber_median": 45.859405517578125,
        "ber_mean": 374.3624572753906
    },
    "374": {
        "depressed": "no",
        "phq_score": "2",
        "gender": "female",
        "f0_median": 225.79288096122622,
        "f0_mean": 250.40847792717213,
        "f0_range": 250.1367345602396,
        "zcr_median": 0.052734375,
        "zcr_mean": 0.07971308406549521,
        "rmse_median": 0.007695977576076984,
        "rmse_mean": 0.009034973569214344,
        "ber_median": 49.69721984863281,
        "ber_mean": 242.4127960205078
    },
    "375": {
        "depressed": "no",
        "phq_score": "5",
        "gender": "male",
        "f0_median": 154.22108254079407,
        "f0_mean": 157.55988734250323,
        "f0_range": 335.3812032266685,
        "zcr_median": 0.04296875,
        "zcr_mean": 0.07814684005591055,
        "rmse_median": 0.007855746895074844,
        "rmse_mean": 0.008706443011760712,
        "ber_median": 87.47763061523438,
        "ber_mean": 798.3787231445312
    },
    "376": {
        "depressed": "yes",
        "phq_score": "12",
        "gender": "female",
        "f0_median": 240.60500721642333,
        "f0_mean": 238.69281755568485,
        "f0_range": 375.4131833907849,
        "zcr_median": 0.044921875,
        "zcr_mean": 0.0606997553913738,
        "rmse_median": 0.008005812764167786,
        "rmse_mean": 0.009365763515233994,
        "ber_median": 107.44459533691406,
        "ber_mean": 750.7379760742188
    },
    "379": {
        "depressed": "no",
        "phq_score": "2",
        "gender": "male",
        "f0_median": 120.99940892192926,
        "f0_mean": 123.73577165428775,
        "f0_range": 67.2106416577019,
        "zcr_median": 0.046875,
        "zcr_mean": 0.07626547523961662,
        "rmse_median": 0.010361546650528908,
        "rmse_mean": 0.011571123264729977,
        "ber_median": 49.300994873046875,
        "ber_mean": 222.3258056640625
    },
    "380": {
        "depressed": "yes",
        "phq_score": "10",
        "gender": "male",
        "f0_median": 220.63576443274928,
        "f0_mean": 218.639667348379,
        "f0_range": 349.6494369654888,
        "zcr_median": 0.0576171875,
        "zcr_mean": 0.12144007088658147,
        "rmse_median": 0.008245034143328667,
        "rmse_mean": 0.017420228570699692,
        "ber_median": 22.688705444335938,
        "ber_mean": 190.36463928222656
    },
    "383": {
        "depressed": "no",
        "phq_score": "7",
        "gender": "male",
        "f0_median": 175.11872228117704,
        "f0_mean": 192.50811963888896,
        "f0_range": 304.75371727660945,
        "zcr_median": 0.044921875,
        "zcr_mean": 0.07244658546325879,
        "rmse_median": 0.006245679222047329,
        "rmse_mean": 0.008817022666335106,
        "ber_median": 78.53756713867188,
        "ber_mean": 495.8383483886719
    },
    "385": {
        "depressed": "no",
        "phq_score": "8",
        "gender": "male",
        "f0_median": 140.60682916223496,
        "f0_mean": 147.1377858020692,
        "f0_range": 296.2023574057108,
        "zcr_median": 0.02734375,
        "zcr_mean": 0.05803838857827476,
        "rmse_median": 0.0021223409567028284,
        "rmse_mean": 0.004697959404438734,
        "ber_median": 95.54313659667969,
        "ber_mean": 443.24774169921875
    },
    "386": {
        "depressed": "yes",
        "phq_score": "11",
        "gender": "female",
        "f0_median": 254.91212546385245,
        "f0_mean": 263.59327998955945,
        "f0_range": 259.5111729122516,
        "zcr_median": 0.0625,
        "zcr_mean": 0.12986097244408945,
        "rmse_median": 0.004743329714983702,
        "rmse_mean": 0.008638403378427029,
        "ber_median": 34.712615966796875,
        "ber_mean": 387.7806396484375
    },
    "391": {
        "depressed": "no",
        "phq_score": "9",
        "gender": "female",
        "f0_median": 281.2136583244699,
        "f0_mean": 294.3214318764769,
        "f0_range": 268.20965833680066,
        "zcr_median": 0.046875,
        "zcr_mean": 0.0644219249201278,
        "rmse_median": 0.010546417906880379,
        "rmse_mean": 0.011619546450674534,
        "ber_median": 67.78656005859375,
        "ber_mean": 1953.48583984375
    },
    "392": {
        "depressed": "no",
        "phq_score": "1",
        "gender": "female",
        "f0_median": 251.98420997897463,
        "f0_mean": 261.3712024294506,
        "f0_range": 267.21119994908554,
        "zcr_median": 0.06640625,
        "zcr_mean": 0.11170252595846646,
        "rmse_median": 0.00559587636962533,
        "rmse_mean": 0.0065209767781198025,
        "ber_median": 22.60887908935547,
        "ber_mean": 179.31422424316406
    },
    "393": {
        "depressed": "no",
        "phq_score": "2",
        "gender": "male",
        "f0_median": 137.3953647458089,
        "f0_mean": 136.69828496451592,
        "f0_range": 69.41232751685361,
        "zcr_median": 0.046875,
        "zcr_mean": 0.08881414736421725,
        "rmse_median": 0.0035626098979264498,
        "rmse_mean": 0.0036890690680593252,
        "ber_median": 122.25814819335938,
        "ber_mean": 388.51458740234375
    },
    "397": {
        "depressed": "no",
        "phq_score": "5",
        "gender": "male",
        "f0_median": 125.99210498948732,
        "f0_mean": 132.98746846861593,
        "f0_range": 114.40863083984694,
        "zcr_median": 0.041015625,
        "zcr_mean": 0.06383224341054312,
        "rmse_median": 0.004279955290257931,
        "rmse_mean": 0.0061055198311805725,
        "ber_median": 55.97443771362305,
        "ber_mean": 243.121826171875
    },
    "400": {
        "depressed": "no",
        "phq_score": "7",
        "gender": "male",
        "f0_median": 99.42404238175475,
        "f0_mean": 99.70443172803381,
        "f0_range": 59.01166218360444,
        "zcr_median": 0.0439453125,
        "zcr_mean": 0.0781874001597444,
        "rmse_median": 0.004253437742590904,
        "rmse_mean": 0.005838803015649319,
        "ber_median": 54.58038330078125,
        "ber_mean": 310.8692626953125
    },
    "401": {
        "depressed": "no",
        "phq_score": "9",
        "gender": "female",
        "f0_median": 241.99881784385852,
        "f0_mean": 244.45469624343806,
        "f0_range": 242.80904434904804,
        "zcr_median": 0.05078125,
        "zcr_mean": 0.07654939596645367,
        "rmse_median": 0.0032661883160471916,
        "rmse_mean": 0.0032020676881074905,
        "ber_median": 32.9844856262207,
        "ber_mean": 197.4499053955078
    },
    "402": {
        "depressed": "yes",
        "phq_score": "11",
        "gender": "female",
        "f0_median": 229.73967099940702,
        "f0_mean": 225.30538227530005,
        "f0_range": 184.3944521589832,
        "zcr_median": 0.03515625,
        "zcr_mean": 0.07138578274760383,
        "rmse_median": 0.0036437325179576874,
        "rmse_mean": 0.004204395692795515,
        "ber_median": 128.87144470214844,
        "ber_mean": 980.1204223632812
    },
    "409": {
        "depressed": "no",
        "phq_score": "10",
        "gender": "male",
        "f0_median": 131.9507910772894,
        "f0_mean": 141.96769183363438,
        "f0_range": 226.3079615378182,
        "zcr_median": 0.044921875,
        "zcr_mean": 0.07039050019968052,
        "rmse_median": 0.005842483136802912,
        "rmse_mean": 0.007329979445785284,
        "ber_median": 48.49623107910156,
        "ber_mean": 221.6532745361328
    },
    "412": {
        "depressed": "yes",
        "phq_score": "12",
        "gender": "male",
        "f0_median": 154.66777936208376,
        "f0_mean": 161.7540464322515,
        "f0_range": 347.54745501679963,
        "zcr_median": 0.033203125,
        "zcr_mean": 0.05745494708466454,
        "rmse_median": 0.0038899967912584543,
        "rmse_mean": 0.004937777295708656,
        "ber_median": 112.78166961669922,
        "ber_mean": 838.9163208007812
    },
    "414": {
        "depressed": "yes",
        "phq_score": "16",
        "gender": "female",
        "f0_median": 289.4538474880756,
        "f0_mean": 294.4294899323578,
        "f0_range": 328.6570933319058,
        "zcr_median": 0.046875,
        "zcr_mean": 0.05992911341853035,
        "rmse_median": 0.005350360181182623,
        "rmse_mean": 0.007433400955051184,
        "ber_median": 98.57408142089844,
        "ber_mean": 728.636962890625
    },
    "415": {
        "depressed": "no",
        "phq_score": "3",
        "gender": "female",
        "f0_median": 259.3679109302019,
        "f0_mean": 271.33785573139016,
        "f0_range": 380.44070865127264,
        "zcr_median": 0.05078125,
        "zcr_mean": 0.08109212759584665,
        "rmse_median": 0.0071564484387636185,
        "rmse_mean": 0.008731761015951633,
        "ber_median": 47.213043212890625,
        "ber_mean": 404.889892578125
    },
    "416": {
        "depressed": "no",
        "phq_score": "3",
        "gender": "male",
        "f0_median": 113.55044290708773,
        "f0_mean": 122.8303911576439,
        "f0_range": 145.40518495137397,
        "zcr_median": 0.046875,
        "zcr_mean": 0.06725177216453675,
        "rmse_median": 0.003379272995516658,
        "rmse_mean": 0.0038012948352843523,
        "ber_median": 32.322933197021484,
        "ber_mean": 169.92312622070312
    },
    "419": {
        "depressed": "no",
        "phq_score": "3",
        "gender": "female",
        "f0_median": 237.8414230005442,
        "f0_mean": 260.1701189396984,
        "f0_range": 286.2948316171378,
        "zcr_median": 0.046875,
        "zcr_mean": 0.06235959964057508,
        "rmse_median": 0.004367042798548937,
        "rmse_mean": 0.005277828313410282,
        "ber_median": 62.91851806640625,
        "ber_mean": 282.1169738769531
    },
    "423": {
        "depressed": "no",
        "phq_score": "0",
        "gender": "female",
        "f0_median": 224.49240966187455,
        "f0_mean": 216.0881500298971,
        "f0_range": 200.78229850917995,
        "zcr_median": 0.068359375,
        "zcr_mean": 0.10365914536741214,
        "rmse_median": 0.005658446811139584,
        "rmse_mean": 0.006579892709851265,
        "ber_median": 23.967487335205078,
        "ber_mean": 139.84347534179688
    },
    "425": {
        "depressed": "no",
        "phq_score": "6",
        "gender": "female",
        "f0_median": 256.3888163841458,
        "f0_mean": 258.19063877881683,
        "f0_range": 306.9075128875936,
        "zcr_median": 0.048828125,
        "zcr_mean": 0.05287477535942492,
        "rmse_median": 0.0044187381863594055,
        "rmse_mean": 0.004175209905952215,
        "ber_median": 71.34344482421875,
        "ber_mean": 512.0263671875
    },
    "426": {
        "depressed": "yes",
        "phq_score": "20",
        "gender": "male",
        "f0_median": 167.2106416577019,
        "f0_mean": 167.70724485351312,
        "f0_range": 230.9265542930256,
        "zcr_median": 0.033203125,
        "zcr_mean": 0.07035306010383387,
        "rmse_median": 0.00405901949852705,
        "rmse_mean": 0.004804018884897232,
        "ber_median": 149.07534790039062,
        "ber_mean": 507.2966613769531
    },
    "427": {
        "depressed": "no",
        "phq_score": "5",
        "gender": "female",
        "f0_median": 213.12010032569688,
        "f0_mean": 219.56876628899377,
        "f0_range": 301.05341532085384,
        "zcr_median": 0.044921875,
        "zcr_mean": 0.06360760283546325,
        "rmse_median": 0.0017799513880163431,
        "rmse_mean": 0.003455830505117774,
        "ber_median": 54.74098205566406,
        "ber_mean": 922.3974609375
    },
    "428": {
        "depressed": "no",
        "phq_score": "0",
        "gender": "male",
        "f0_median": 170.13343219017113,
        "f0_mean": 178.11010799902206,
        "f0_range": 230.56599807140032,
        "zcr_median": 0.044921875,
        "zcr_mean": 0.0636138428514377,
        "rmse_median": 0.004339983686804771,
        "rmse_mean": 0.005456977058202028,
        "ber_median": 44.55321502685547,
        "ber_mean": 748.3820190429688
    },
    "429": {
        "depressed": "no",
        "phq_score": "1",
        "gender": "male",
        "f0_median": 176.6433392698509,
        "f0_mean": 181.52133545539004,
        "f0_range": 160.13708149756434,
        "zcr_median": 0.05859375,
        "zcr_mean": 0.11178052615814696,
        "rmse_median": 0.003017605748027563,
        "rmse_mean": 0.004571953322738409,
        "ber_median": 28.098491668701172,
        "ber_mean": 159.82823181152344
    },
    "430": {
        "depressed": "no",
        "phq_score": "3",
        "gender": "male",
        "f0_median": 133.48398541700342,
        "f0_mean": 134.17855196803401,
        "f0_range": 367.7536474807399,
        "zcr_median": 0.04296875,
        "zcr_mean": 0.06631888977635783,
        "rmse_median": 0.002584128873422742,
        "rmse_mean": 0.0037834320683032274,
        "ber_median": 67.99436950683594,
        "ber_mean": 367.14556884765625
    },
    "433": {
        "depressed": "yes",
        "phq_score": "10",
        "gender": "male",
        "f0_median": 121.7003513670591,
        "f0_mean": 122.50411136401497,
        "f0_range": 44.39431039741052,
        "zcr_median": 0.046875,
        "zcr_mean": 0.06398200379392971,
        "rmse_median": 0.003737843129783869,
        "rmse_mean": 0.0041799722239375114,
        "ber_median": 65.41160583496094,
        "ber_mean": 146.5791473388672
    },
    "434": {
        "depressed": "no",
        "phq_score": "2",
        "gender": "male",
        "f0_median": 156.0130452026747,
        "f0_mean": 158.5140468913277,
        "f0_range": 361.8880111187866,
        "zcr_median": 0.056640625,
        "zcr_mean": 0.06696785143769968,
        "rmse_median": 0.006913026794791222,
        "rmse_mean": 0.009273852221667767,
        "ber_median": 25.490760803222656,
        "ber_mean": 376.8718566894531
    },
    "437": {
        "depressed": "no",
        "phq_score": "0",
        "gender": "male",
        "f0_median": 143.06459324352582,
        "f0_mean": 148.562888050408,
        "f0_range": 162.58371549893855,
        "zcr_median": 0.03515625,
        "zcr_mean": 0.0541227785543131,
        "rmse_median": 0.003036526031792164,
        "rmse_mean": 0.0027503296732902527,
        "ber_median": 276.2642822265625,
        "ber_mean": 788.6325073242188
    },
    "441": {
        "depressed": "yes",
        "phq_score": "18",
        "gender": "female",
        "f0_median": 176.1331747192297,
        "f0_mean": 176.7700427676589,
        "f0_range": 150.96690899381673,
        "zcr_median": 0.05859375,
        "zcr_mean": 0.08555685902555911,
        "rmse_median": 0.00230947183445096,
        "rmse_mean": 0.003016456263139844,
        "ber_median": 40.197532653808594,
        "ber_mean": 199.7080535888672
    },
    "443": {
        "depressed": "no",
        "phq_score": "1",
        "gender": "male",
        "f0_median": 120.99940892192926,
        "f0_mean": 121.46104865188616,
        "f0_range": 77.45313140582259,
        "zcr_median": 0.046875,
        "zcr_mean": 0.07584427416134186,
        "rmse_median": 0.004863377194851637,
        "rmse_mean": 0.006795343942940235,
        "ber_median": 119.712646484375,
        "ber_mean": 405.1160583496094
    },
    "444": {
        "depressed": "no",
        "phq_score": "7",
        "gender": "female",
        "f0_median": 220.63576443274928,
        "f0_mean": 227.91608116054144,
        "f0_range": 374.09171237556967,
        "zcr_median": 0.05859375,
        "zcr_mean": 0.0823214107428115,
        "rmse_median": 0.004384765401482582,
        "rmse_mean": 0.006112562958151102,
        "ber_median": 26.43120574951172,
        "ber_mean": 171.9665985107422
    },
    "445": {
        "depressed": "no",
        "phq_score": "1",
        "gender": "male",
        "f0_median": 141.4213562373095,
        "f0_mean": 141.90210537217808,
        "f0_range": 94.05369056407046,
        "zcr_median": 0.048828125,
        "zcr_mean": 0.06587584864217252,
        "rmse_median": 0.006078712642192841,
        "rmse_mean": 0.006475044880062342,
        "ber_median": 41.75140380859375,
        "ber_mean": 227.1326141357422
    },
    "446": {
        "depressed": "no",
        "phq_score": "0",
        "gender": "female",
        "f0_median": 200.57929410678534,
        "f0_mean": 216.40990535422912,
        "f0_range": 283.70592540556305,
        "zcr_median": 0.05078125,
        "zcr_mean": 0.06308968150958466,
        "rmse_median": 0.003876302856951952,
        "rmse_mean": 0.0040083471685647964,
        "ber_median": 61.004188537597656,
        "ber_mean": 381.90020751953125
    },
    "447": {
        "depressed": "no",
        "phq_score": "1",
        "gender": "male",
        "f0_median": 155.56376069302408,
        "f0_mean": 155.2602609111671,
        "f0_range": 401.2855164821447,
        "zcr_median": 0.052734375,
        "zcr_mean": 0.07672411641373802,
        "rmse_median": 0.004118152894079685,
        "rmse_mean": 0.005201669875532389,
        "ber_median": 40.526031494140625,
        "ber_mean": 171.3408660888672
    },
    "448": {
        "depressed": "yes",
        "phq_score": "18",
        "gender": "male",
        "f0_median": 166.24757922855756,
        "f0_mean": 170.64490083317648,
        "f0_range": 273.30919674533754,
        "zcr_median": 0.05078125,
        "zcr_mean": 0.07354482827476039,
        "rmse_median": 0.004928385838866234,
        "rmse_mean": 0.0063459910452365875,
        "ber_median": 54.05836486816406,
        "ber_mean": 406.8129577636719
    },
    "449": {
        "depressed": "no",
        "phq_score": "2",
        "gender": "female",
        "f0_median": 187.68759933422865,
        "f0_mean": 200.6952940410462,
        "f0_range": 270.598735113314,
        "zcr_median": 0.05078125,
        "zcr_mean": 0.06475264576677316,
        "rmse_median": 0.007096695713698864,
        "rmse_mean": 0.006704476661980152,
        "ber_median": 71.07830810546875,
        "ber_mean": 381.6900329589844
    },
    "454": {
        "depressed": "no",
        "phq_score": "1",
        "gender": "female",
        "f0_median": 253.44393965741244,
        "f0_mean": 261.9772018390467,
        "f0_range": 256.53724430009527,
        "zcr_median": 0.048828125,
        "zcr_mean": 0.080078125,
        "rmse_median": 0.0025732978247106075,
        "rmse_mean": 0.003831717185676098,
        "ber_median": 67.0506820678711,
        "ber_mean": 321.639404296875
    },
    "455": {
        "depressed": "no",
        "phq_score": "1",
        "gender": "female",
        "f0_median": 201.15858821357068,
        "f0_mean": 210.96336853982027,
        "f0_range": 295.10044023226646,
        "zcr_median": 0.044921875,
        "zcr_mean": 0.057635907547923325,
        "rmse_median": 0.003428870579227805,
        "rmse_mean": 0.004173522815108299,
        "ber_median": 65.86656188964844,
        "ber_mean": 489.1545104980469
    },
    "456": {
        "depressed": "no",
        "phq_score": "6",
        "gender": "female",
        "f0_median": 216.8453740602837,
        "f0_mean": 221.41096717333068,
        "f0_range": 271.90297318946443,
        "zcr_median": 0.04296875,
        "zcr_mean": 0.066590330471246,
        "rmse_median": 0.0071549806743860245,
        "rmse_mean": 0.007269499823451042,
        "ber_median": 104.08447265625,
        "ber_mean": 673.1063842773438
    },
    "457": {
        "depressed": "no",
        "phq_score": "3",
        "gender": "male",
        "f0_median": 128.9370308439579,
        "f0_mean": 131.41365477636165,
        "f0_range": 79.27459338745358,
        "zcr_median": 0.041015625,
        "zcr_mean": 0.05643782448083067,
        "rmse_median": 0.0024867751635611057,
        "rmse_mean": 0.0036677918396890163,
        "ber_median": 67.05781555175781,
        "ber_mean": 377.55072021484375
    },
    "459": {
        "depressed": "yes",
        "phq_score": "16",
        "gender": "male",
        "f0_median": 124.5449622358823,
        "f0_mean": 126.66665872082287,
        "f0_range": 360.69690957992196,
        "zcr_median": 0.0478515625,
        "zcr_mean": 0.06971657847444089,
        "rmse_median": 0.002306920476257801,
        "rmse_mean": 0.002650662325322628,
        "ber_median": 25.92422103881836,
        "ber_mean": 126.09260559082031
    },
    "463": {
        "depressed": "no",
        "phq_score": "0",
        "gender": "male",
        "f0_median": 147.25670581005258,
        "f0_mean": 149.68052561598543,
        "f0_range": 79.45823684651158,
        "zcr_median": 0.052734375,
        "zcr_mean": 0.10129729932108626,
        "rmse_median": 0.005502908490598202,
        "rmse_mean": 0.0062756468541920185,
        "ber_median": 24.704750061035156,
        "ber_mean": 112.97085571289062
    },
    "464": {
        "depressed": "no",
        "phq_score": "0",
        "gender": "male",
        "f0_median": 128.9370308439579,
        "f0_mean": 130.57068672490144,
        "f0_range": 321.44784854404065,
        "zcr_median": 0.0478515625,
        "zcr_mean": 0.08011244508785942,
        "rmse_median": 0.005627521313726902,
        "rmse_mean": 0.007020013406872749,
        "ber_median": 41.6665153503418,
        "ber_mean": 304.1703186035156
    },
    "468": {
        "depressed": "no",
        "phq_score": "4",
        "gender": "male",
        "f0_median": 161.5148333600084,
        "f0_mean": 166.54262695897685,
        "f0_range": 114.0662028749641,
        "zcr_median": 0.044921875,
        "zcr_mean": 0.05538014177316294,
        "rmse_median": 0.005845285020768642,
        "rmse_mean": 0.006462342571467161,
        "ber_median": 76.34457397460938,
        "ber_mean": 428.859130859375
    },
    "471": {
        "depressed": "no",
        "phq_score": "0",
        "gender": "male",
        "f0_median": 131.9507910772894,
        "f0_mean": 132.16188409948822,
        "f0_range": 90.64713534281104,
        "zcr_median": 0.0390625,
        "zcr_mean": 0.052225813698083066,
        "rmse_median": 0.003820398822426796,
        "rmse_mean": 0.004733456298708916,
        "ber_median": 59.556610107421875,
        "ber_mean": 280.7444763183594
    },
    "473": {
        "depressed": "no",
        "phq_score": "0",
        "gender": "female",
        "f0_median": 204.67477839935495,
        "f0_mean": 202.9611035928308,
        "f0_range": 289.1887340796876,
        "zcr_median": 0.0546875,
        "zcr_mean": 0.07756339856230032,
        "rmse_median": 0.005405129864811897,
        "rmse_mean": 0.006104276515543461,
        "ber_median": 26.359447479248047,
        "ber_mean": 320.63397216796875
    },
    "474": {
        "depressed": "no",
        "phq_score": "4",
        "gender": "male",
        "f0_median": 141.4213562373095,
        "f0_mean": 142.17830683052753,
        "f0_range": 91.16922442453907,
        "zcr_median": 0.052734375,
        "zcr_mean": 0.08440245607028754,
        "rmse_median": 0.00882323831319809,
        "rmse_mean": 0.011196566745638847,
        "ber_median": 43.808631896972656,
        "ber_mean": 206.42893981933594
    },
    "475": {
        "depressed": "no",
        "phq_score": "6",
        "gender": "male",
        "f0_median": 140.60682916223496,
        "f0_mean": 140.6335297756723,
        "f0_range": 235.67796011019243,
        "zcr_median": 0.04296875,
        "zcr_mean": 0.05444725938498403,
        "rmse_median": 0.004504794254899025,
        "rmse_mean": 0.00449278112500906,
        "ber_median": 46.104366302490234,
        "ber_mean": 224.97927856445312
    },
    "478": {
        "depressed": "no",
        "phq_score": "1",
        "gender": "female",
        "f0_median": 270.06998923363795,
        "f0_mean": 284.15776269622415,
        "f0_range": 364.2633571458935,
        "zcr_median": 0.095703125,
        "zcr_mean": 0.10910979932108626,
        "rmse_median": 0.003875564318150282,
        "rmse_mean": 0.005319928750395775,
        "ber_median": 7.254960060119629,
        "ber_mean": 67.07488250732422
    },
    "479": {
        "depressed": "no",
        "phq_score": "7",
        "gender": "male",
        "f0_median": 133.8706178475149,
        "f0_mean": 134.24867538581492,
        "f0_range": 73.69004235931764,
        "zcr_median": 0.0390625,
        "zcr_mean": 0.049342926317891375,
        "rmse_median": 0.002703243400901556,
        "rmse_mean": 0.0025935431476682425,
        "ber_median": 128.27554321289062,
        "ber_mean": 453.58795166015625
    },
    "485": {
        "depressed": "no",
        "phq_score": "2",
        "gender": "male",
        "f0_median": 175.11872228117704,
        "f0_mean": 179.10347816099443,
        "f0_range": 112.4954583830638,
        "zcr_median": 0.06640625,
        "zcr_mean": 0.08704822284345048,
        "rmse_median": 0.004077705554664135,
        "rmse_mean": 0.0045126634649932384,
        "ber_median": 15.58163833618164,
        "ber_mean": 86.87774658203125
    },
    "486": {
        "depressed": "no",
        "phq_score": "4",
        "gender": "female",
        "f0_median": 172.11028744886602,
        "f0_mean": 176.06881322645827,
        "f0_range": 177.34792605396453,
        "zcr_median": 0.0546875,
        "zcr_mean": 0.08017172523961662,
        "rmse_median": 0.005656227935105562,
        "rmse_mean": 0.006531141698360443,
        "ber_median": 45.98566436767578,
        "ber_mean": 257.38311767578125
    },
    "487": {
        "depressed": "no",
        "phq_score": "0",
        "gender": "female",
        "f0_median": 259.3679109302019,
        "f0_mean": 263.909312483605,
        "f0_range": 267.03635133595435,
        "zcr_median": 0.056640625,
        "zcr_mean": 0.08348829373003194,
        "rmse_median": 0.0028052879497408867,
        "rmse_mean": 0.0028721867129206657,
        "ber_median": 71.51823425292969,
        "ber_mean": 374.30322265625
    },
    "488": {
        "depressed": "no",
        "phq_score": "0",
        "gender": "female",
        "f0_median": 250.53288772482563,
        "f0_mean": 247.74312001980698,
        "f0_range": 351.0566549686722,
        "zcr_median": 0.0546875,
        "zcr_mean": 0.07728883785942492,
        "rmse_median": 0.002774505876004696,
        "rmse_mean": 0.0030169403180480003,
        "ber_median": 31.637514114379883,
        "ber_mean": 160.9341583251953
    },
    "491": {
        "depressed": "no",
        "phq_score": "8",
        "gender": "female",
        "f0_median": 218.10154653305153,
        "f0_mean": 226.77255338372476,
        "f0_range": 253.50885614816292,
        "zcr_median": 0.05859375,
        "zcr_mean": 0.07226874500798722,
        "rmse_median": 0.004955001175403595,
        "rmse_mean": 0.008347666822373867,
        "ber_median": 48.70604705810547,
        "ber_mean": 316.4034423828125
    }
}
